{"version":3,"kind":"Article","sha256":"56bc2ba1eeef56f718c93259c8e6398220e574e67e1d27c56a62cba0688fdb7c","slug":"index","location":"/README.md","dependencies":[],"frontmatter":{"title":"Aerosol Cloud Interaction Cookbook","content_includes_title":false,"authors":[{"nameParsed":{"literal":"The Project Pythia Community","given":"The Project Pythia","family":"Community"},"name":"The Project Pythia Community","id":"contributors-myst-generated-uid-0"}],"open_access":true,"license":{"content":{"id":"CC-BY-4.0","url":"https://creativecommons.org/licenses/by/4.0/","name":"Creative Commons Attribution 4.0 International","free":true,"CC":true},"code":{"id":"Apache-2.0","url":"https://opensource.org/licenses/Apache-2.0","name":"Apache License 2.0","free":true,"osi":true}},"github":"https://github.com/projectpythia/cookbook-template","copyright":"2024","affiliations":[{"id":"UAlbany","name":"University at Albany (SUNY)","department":"Atmospheric and Environmental Sciences","url":"https://www.albany.edu/daes"},{"id":"CISL","name":"NSF National Center for Atmospheric Research","department":"Computational and Information Systems Lab","url":"https://www.cisl.ucar.edu"},{"id":"Unidata","name":"NSF Unidata","url":"https://www.unidata.ucar.edu"},{"id":"Argonne","name":"Argonne National Laboratory","department":"Environmental Science Division","url":"https://www.anl.gov/evs"},{"id":"CarbonPlan","name":"CarbonPlan","url":"https://carbonplan.org"},{"id":"NVIDIA","name":"NVIDIA Corporation","url":"https://www.nvidia.com/"}],"source_url":"https://github.com/projectpythia/cookbook-template/blob/main/README.md","edit_url":"https://github.com/projectpythia/cookbook-template/edit/main/README.md","thumbnail":"/Aerosol-Cloud-Interactions-cookbook/build/thumbnail-f5a999adc937e6f6ea7d6f9e3e74d2f1.png","exports":[{"format":"md","filename":"README.md","url":"/Aerosol-Cloud-Interactions-cookbook/build/README-2b887b74a3110275ce381aecc923cbe3.md"}]},"mdast":{"type":"root","children":[{"type":"block","children":[{"type":"image","url":"/Aerosol-Cloud-Interactions-cookbook/build/thumbnail-f5a999adc937e6f6ea7d6f9e3e74d2f1.png","alt":"thumbnail","width":300,"key":"rieIs9GJES","urlSource":"thumbnails/thumbnail.png"},{"type":"paragraph","position":{"start":{"line":5,"column":1},"end":{"line":7,"column":1}},"children":[{"type":"link","url":"https://github.com/ProjectPythia/cookbook-template/actions/workflows/nightly-build.yaml","position":{"start":{"line":5,"column":1},"end":{"line":5,"column":1}},"children":[{"type":"image","url":"/Aerosol-Cloud-Interactions-cookbook/build/06605fa84b8680f0497b7822b6283a3e.svg","alt":"nightly-build","position":{"start":{"line":5,"column":1},"end":{"line":5,"column":1}},"key":"VQHHeBtxR8","urlSource":"https://github.com/ProjectPythia/cookbook-template/actions/workflows/nightly-build.yaml/badge.svg"}],"urlSource":"https://github.com/ProjectPythia/cookbook-template/actions/workflows/nightly-build.yaml","error":true,"key":"FcruK7CLIa"},{"type":"text","value":"\n","position":{"start":{"line":5,"column":1},"end":{"line":5,"column":1}},"key":"ApJtsV8Mep"},{"type":"link","url":"https://binder.projectpythia.org/v2/gh/ProjectPythia/cookbook-template/main?labpath=notebooks","position":{"start":{"line":5,"column":1},"end":{"line":5,"column":1}},"children":[{"type":"image","url":"/Aerosol-Cloud-Interactions-cookbook/build/31e3f387ea168934ca949c27e9927ea4.svg","alt":"Binder","position":{"start":{"line":5,"column":1},"end":{"line":5,"column":1}},"key":"pRdTmXFvyC","urlSource":"https://binder.projectpythia.org/badge_logo.svg"}],"urlSource":"https://binder.projectpythia.org/v2/gh/ProjectPythia/cookbook-template/main?labpath=notebooks","key":"K87GI5jJ4y"},{"type":"text","value":"\n","position":{"start":{"line":5,"column":1},"end":{"line":5,"column":1}},"key":"I8ucAhxik9"},{"type":"link","url":"https://doi.org/10.5281/zenodo.475509405","position":{"start":{"line":5,"column":1},"end":{"line":5,"column":1}},"children":[{"type":"image","url":"/Aerosol-Cloud-Interactions-cookbook/build/72a08caa5cbe5f9cce5999dbd1a81dfd.svg","alt":"DOI","position":{"start":{"line":5,"column":1},"end":{"line":5,"column":1}},"key":"bqCXA63Ywt","urlSource":"https://zenodo.org/badge/475509405.svg"}],"urlSource":"https://zenodo.org/badge/latestdoi/475509405","data":{"doi":"10.5281/zenodo.475509405"},"internal":false,"protocol":"doi","key":"nhk98YixU6"}],"key":"z8dwuLK0tP"},{"type":"paragraph","position":{"start":{"line":9,"column":1},"end":{"line":9,"column":1}},"children":[{"type":"emphasis","position":{"start":{"line":9,"column":1},"end":{"line":9,"column":1}},"children":[{"type":"text","value":"See the ","position":{"start":{"line":9,"column":1},"end":{"line":9,"column":1}},"key":"rTBO0dYvmU"},{"type":"link","url":"https://projectpythia.org/cookbook-guide","position":{"start":{"line":9,"column":1},"end":{"line":9,"column":1}},"children":[{"type":"text","value":"Cookbook Contributor’s Guide","position":{"start":{"line":9,"column":1},"end":{"line":9,"column":1}},"key":"aCwrckv6G6"}],"urlSource":"https://projectpythia.org/cookbook-guide","key":"ibArboVn6F"},{"type":"text","value":" for step-by-step instructions on how to create your new Cookbook and get it hosted on the ","position":{"start":{"line":9,"column":1},"end":{"line":9,"column":1}},"key":"yy1QTm543q"},{"type":"link","url":"https://cookbooks.projectpythia.org","position":{"start":{"line":9,"column":1},"end":{"line":9,"column":1}},"children":[{"type":"text","value":"Pythia Cookbook Gallery","position":{"start":{"line":9,"column":1},"end":{"line":9,"column":1}},"key":"e7JTybgXPv"}],"urlSource":"https://cookbooks.projectpythia.org","key":"onwpvB3rTg"},{"type":"text","value":"!","position":{"start":{"line":9,"column":1},"end":{"line":9,"column":1}},"key":"KeJsMIP63J"}],"key":"JvuEbEpc7o"}],"key":"Eyqo24awk9"},{"type":"paragraph","position":{"start":{"line":11,"column":1},"end":{"line":11,"column":1}},"children":[{"type":"text","value":"This Project Pythia Cookbook covers ... (replace ","position":{"start":{"line":11,"column":1},"end":{"line":11,"column":1}},"key":"uKtGBp3fI7"},{"type":"inlineCode","value":"...","position":{"start":{"line":11,"column":1},"end":{"line":11,"column":1}},"key":"FKA5xDMmPB"},{"type":"text","value":" with the main subject of your cookbook ... e.g., ","position":{"start":{"line":11,"column":1},"end":{"line":11,"column":1}},"key":"KAFK1QvqxN"},{"type":"emphasis","position":{"start":{"line":11,"column":1},"end":{"line":11,"column":1}},"children":[{"type":"text","value":"working with radar data in Python","position":{"start":{"line":11,"column":1},"end":{"line":11,"column":1}},"key":"o6LIF2SAUQ"}],"key":"W75b8NsM6s"},{"type":"text","value":")","position":{"start":{"line":11,"column":1},"end":{"line":11,"column":1}},"key":"WPtycNFcJk"}],"key":"RkBWXV5zdK"},{"type":"heading","depth":2,"position":{"start":{"line":13,"column":1},"end":{"line":13,"column":1}},"children":[{"type":"text","value":"Motivation","position":{"start":{"line":13,"column":1},"end":{"line":13,"column":1}},"key":"pGhLIhxlND"}],"identifier":"motivation","label":"Motivation","html_id":"motivation","implicit":true,"key":"HiiwYzxVIo"},{"type":"paragraph","position":{"start":{"line":15,"column":1},"end":{"line":15,"column":1}},"children":[{"type":"text","value":"Aerosol-cloud interactions (ACIs) continue to introduce the greatest degree of uncertainty into the estimate of effective radiative forcing, which affects our ability to project temperature/precipitation evolution and assess societal risks. It is challenging to represent ACIs in models because they involve multiscale and nonlinear processes.  Comparing simulated ACIs from different models and evaluating model performance will help us understand processes and reduce projection uncertainty.","position":{"start":{"line":15,"column":1},"end":{"line":15,"column":1}},"key":"A3tdIqc2PU"}],"key":"zlPB81j4bk"},{"type":"paragraph","position":{"start":{"line":17,"column":1},"end":{"line":17,"column":1}},"children":[{"type":"text","value":"This cook book provide overview of Aerosol and Clouds for understanding of high school students. Aerosol dataset from CIMP6 project to","position":{"start":{"line":17,"column":1},"end":{"line":17,"column":1}},"key":"SR3zN3mrod"}],"key":"mFqU6TVyz2"},{"type":"heading","depth":2,"position":{"start":{"line":19,"column":1},"end":{"line":19,"column":1}},"children":[{"type":"text","value":"Authors","position":{"start":{"line":19,"column":1},"end":{"line":19,"column":1}},"key":"bl9qCnA0ne"}],"identifier":"authors","label":"Authors","html_id":"authors","implicit":true,"key":"h4qnFM7sCh"},{"type":"paragraph","position":{"start":{"line":21,"column":1},"end":{"line":21,"column":1}},"children":[{"type":"text","value":"First Author, Second Author, etc. ","position":{"start":{"line":21,"column":1},"end":{"line":21,"column":1}},"key":"aAPWS669yc"},{"type":"emphasis","position":{"start":{"line":21,"column":1},"end":{"line":21,"column":1}},"children":[{"type":"text","value":"Acknowledge primary content authors here! You can include links to their GitHub profiles or other unique pages.","position":{"start":{"line":21,"column":1},"end":{"line":21,"column":1}},"key":"I0z4puYyEi"}],"key":"RgkzXjSttf"}],"key":"RvF2UnHQ3m"},{"type":"heading","depth":3,"position":{"start":{"line":23,"column":1},"end":{"line":23,"column":1}},"children":[{"type":"text","value":"Contributors","position":{"start":{"line":23,"column":1},"end":{"line":23,"column":1}},"key":"CZ2gsCfkeo"}],"identifier":"contributors","label":"Contributors","html_id":"contributors","implicit":true,"key":"QG6m5bN2bE"},{"type":"link","url":"https://github.com/ProjectPythia/Aerosol-Cloud-Interactions-cookbook/graphs/contributors","children":[{"type":"image","url":"/Aerosol-Cloud-Interactions-cookbook/build/805028e68202d488d79799a7fbd3a61d.svg","key":"f0hguyg7f7","urlSource":"https://contrib.rocks/image?repo=ProjectPythia/Aerosol-Cloud-Interactions-cookbook"}],"urlSource":"https://github.com/ProjectPythia/Aerosol-Cloud-Interactions-cookbook/graphs/contributors","error":true,"key":"F8mptWvbmn"},{"type":"heading","depth":2,"position":{"start":{"line":29,"column":1},"end":{"line":29,"column":1}},"children":[{"type":"text","value":"Structure","position":{"start":{"line":29,"column":1},"end":{"line":29,"column":1}},"key":"Hk6DztToDg"}],"identifier":"structure","label":"Structure","html_id":"structure","implicit":true,"key":"I4k8QQsDBr"},{"type":"paragraph","position":{"start":{"line":31,"column":1},"end":{"line":31,"column":1}},"children":[{"type":"text","value":"(State one or more sections that will comprise the notebook. E.g., ","position":{"start":{"line":31,"column":1},"end":{"line":31,"column":1}},"key":"pXtVcVb4Mq"},{"type":"emphasis","position":{"start":{"line":31,"column":1},"end":{"line":31,"column":1}},"children":[{"type":"text","value":"This cookbook is broken up into two main sections - “Foundations” and “Example Workflows.”","position":{"start":{"line":31,"column":1},"end":{"line":31,"column":1}},"key":"d7FFtrdzI0"}],"key":"dIBIkbTUFV"},{"type":"text","value":" Then, describe each section below.)","position":{"start":{"line":31,"column":1},"end":{"line":31,"column":1}},"key":"MzP0101d7r"}],"key":"syoJT7kqAu"},{"type":"heading","depth":3,"position":{"start":{"line":33,"column":1},"end":{"line":33,"column":1}},"children":[{"type":"text","value":"Section 1 ( Replace with the title of this section, e.g. “Foundations” )","position":{"start":{"line":33,"column":1},"end":{"line":33,"column":1}},"key":"PlQSwApQ8Q"}],"identifier":"section-1-replace-with-the-title-of-this-section-e-g-foundations","label":"Section 1 ( Replace with the title of this section, e.g. “Foundations” )","html_id":"section-1-replace-with-the-title-of-this-section-e-g-foundations","implicit":true,"key":"fwfAqVqeJq"},{"type":"paragraph","position":{"start":{"line":35,"column":1},"end":{"line":35,"column":1}},"children":[{"type":"text","value":"(Add content for this section, e.g., \"The foundational content includes ... \")","position":{"start":{"line":35,"column":1},"end":{"line":35,"column":1}},"key":"EJpUm94Zg2"}],"key":"zdfFSvkcdp"},{"type":"heading","depth":3,"position":{"start":{"line":37,"column":1},"end":{"line":37,"column":1}},"children":[{"type":"text","value":"Section 2 ( Replace with the title of this section, e.g. “Example workflows” )","position":{"start":{"line":37,"column":1},"end":{"line":37,"column":1}},"key":"p58sMHgoyy"}],"identifier":"section-2-replace-with-the-title-of-this-section-e-g-example-workflows","label":"Section 2 ( Replace with the title of this section, e.g. “Example workflows” )","html_id":"section-2-replace-with-the-title-of-this-section-e-g-example-workflows","implicit":true,"key":"V8wOEYy9cw"},{"type":"paragraph","position":{"start":{"line":39,"column":1},"end":{"line":39,"column":1}},"children":[{"type":"text","value":"(Add content for this section, e.g., \"Example workflows include ... \")","position":{"start":{"line":39,"column":1},"end":{"line":39,"column":1}},"key":"EF6IUDARHn"}],"key":"RqAMKvRepH"},{"type":"heading","depth":2,"position":{"start":{"line":41,"column":1},"end":{"line":41,"column":1}},"children":[{"type":"text","value":"Running the Notebooks","position":{"start":{"line":41,"column":1},"end":{"line":41,"column":1}},"key":"jD4R4MifZx"}],"identifier":"running-the-notebooks","label":"Running the Notebooks","html_id":"running-the-notebooks","implicit":true,"key":"fhYecZdyYA"},{"type":"paragraph","position":{"start":{"line":43,"column":1},"end":{"line":43,"column":1}},"children":[{"type":"text","value":"You can either run the notebooks in the Cookbook using ","position":{"start":{"line":43,"column":1},"end":{"line":43,"column":1}},"key":"EoieblPNsn"},{"type":"link","url":"https://binder.projectpythia.org/","position":{"start":{"line":43,"column":1},"end":{"line":43,"column":1}},"children":[{"type":"text","value":"Binder","position":{"start":{"line":43,"column":1},"end":{"line":43,"column":1}},"key":"vI0EpBBUyH"}],"urlSource":"https://binder.projectpythia.org/","key":"qoeBAM2yGk"},{"type":"text","value":" or on your local machine.","position":{"start":{"line":43,"column":1},"end":{"line":43,"column":1}},"key":"Dno5T8DxZT"}],"key":"fkPK0U4WKh"},{"type":"heading","depth":3,"position":{"start":{"line":45,"column":1},"end":{"line":45,"column":1}},"children":[{"type":"text","value":"Running on Binder","position":{"start":{"line":45,"column":1},"end":{"line":45,"column":1}},"key":"qtG9iKgGMp"}],"identifier":"running-on-binder","label":"Running on Binder","html_id":"running-on-binder","implicit":true,"key":"JadVh5Kva1"},{"type":"paragraph","position":{"start":{"line":47,"column":1},"end":{"line":60,"column":1}},"children":[{"type":"text","value":"The simplest way to interact with a Jupyter Notebook is through\n","position":{"start":{"line":47,"column":1},"end":{"line":47,"column":1}},"key":"Izcyj9GYPJ"},{"type":"link","url":"https://binder.projectpythia.org/","position":{"start":{"line":47,"column":1},"end":{"line":47,"column":1}},"children":[{"type":"text","value":"Binder","position":{"start":{"line":47,"column":1},"end":{"line":47,"column":1}},"key":"C3qLliDUhp"}],"urlSource":"https://binder.projectpythia.org/","key":"fEViZpz6ku"},{"type":"text","value":", which enables “one click”\nexecution in the cloud. Simply navigate your mouse to\nthe top right corner of the book chapter you are viewing and click\non the rocket ship icon (see screenshots ","position":{"start":{"line":47,"column":1},"end":{"line":47,"column":1}},"key":"YSjpseNUjp"},{"type":"link","url":"https://foundations.projectpythia.org/preamble/how-to-use/#running-pythia-foundations-examples","position":{"start":{"line":47,"column":1},"end":{"line":47,"column":1}},"children":[{"type":"text","value":"here","position":{"start":{"line":47,"column":1},"end":{"line":47,"column":1}},"key":"czy2ahIoqz"}],"urlSource":"https://foundations.projectpythia.org/preamble/how-to-use/#running-pythia-foundations-examples","key":"Es0bQfWvT5"},{"type":"text","value":"),\nand a text box will appear. Type or paste the Pythia Binder link\n(","position":{"start":{"line":47,"column":1},"end":{"line":47,"column":1}},"key":"yMJZeGeRfM"},{"type":"inlineCode","value":"https://binder.projectpythia.org","position":{"start":{"line":47,"column":1},"end":{"line":47,"column":1}},"key":"XkEgkYm0sf"},{"type":"text","value":") and click “Launch”.\nAfter a few moments you should be presented with a\nnotebook that you can interact with. You’ll be able to execute code\nand even change the example programs. At first the code cells\nhave no output, until you execute them by pressing\n","position":{"start":{"line":47,"column":1},"end":{"line":47,"column":1}},"key":"DMhMoKT7T5"},{"type":"keyboard","children":[{"type":"text","value":"Shift","key":"fvnQYIWvC9"}],"key":"Yp78XbLCkc"},{"type":"text","value":"+","position":{"start":{"line":47,"column":1},"end":{"line":47,"column":1}},"key":"cUnLlkHmbv"},{"type":"keyboard","children":[{"type":"text","value":"Enter","key":"Fznu2z9Rax"}],"key":"Dl9nMO3FlT"},{"type":"text","value":". Complete details on how to interact with\na live Jupyter notebook are described in the Pythia Foundations chapter ","position":{"start":{"line":47,"column":1},"end":{"line":47,"column":1}},"key":"HcnfqHlFnX"},{"type":"link","url":"https://foundations.projectpythia.org/foundations/getting-started-jupyter","position":{"start":{"line":47,"column":1},"end":{"line":47,"column":1}},"children":[{"type":"text","value":"Getting Started with\nJupyter","position":{"start":{"line":47,"column":1},"end":{"line":47,"column":1}},"key":"rMp4rEHu5l"}],"urlSource":"https://foundations.projectpythia.org/foundations/getting-started-jupyter","key":"g9hg5H0Uee"},{"type":"text","value":".","position":{"start":{"line":47,"column":1},"end":{"line":47,"column":1}},"key":"P4fjIDI4HI"}],"key":"c2ifI3FlOg"},{"type":"paragraph","position":{"start":{"line":62,"column":1},"end":{"line":64,"column":1}},"children":[{"type":"text","value":"Note, not all Cookbook chapters are executable. If you do not see\nthe rocket ship icon, such as on this page, you are not viewing an\nexecutable book chapter.","position":{"start":{"line":62,"column":1},"end":{"line":62,"column":1}},"key":"grYlkxwOoI"}],"key":"vJJgus7Uod"},{"type":"heading","depth":3,"position":{"start":{"line":67,"column":1},"end":{"line":67,"column":1}},"children":[{"type":"text","value":"Running on Your Own Machine","position":{"start":{"line":67,"column":1},"end":{"line":67,"column":1}},"key":"GjnWluwBGB"}],"identifier":"running-on-your-own-machine","label":"Running on Your Own Machine","html_id":"running-on-your-own-machine","implicit":true,"key":"wieEr5WTEY"},{"type":"paragraph","position":{"start":{"line":69,"column":1},"end":{"line":69,"column":1}},"children":[{"type":"text","value":"If you are interested in running this material locally on your computer, you will need to follow this workflow:","position":{"start":{"line":69,"column":1},"end":{"line":69,"column":1}},"key":"zHC9bfobDx"}],"key":"awUrZWUlpL"},{"type":"list","ordered":true,"start":1,"spread":false,"position":{"start":{"line":72,"column":1},"end":{"line":91,"column":1}},"children":[{"type":"listItem","spread":true,"position":{"start":{"line":72,"column":1},"end":{"line":77,"column":1}},"children":[{"type":"paragraph","position":{"start":{"line":72,"column":1},"end":{"line":72,"column":1}},"children":[{"type":"text","value":"Clone the ","position":{"start":{"line":72,"column":1},"end":{"line":72,"column":1}},"key":"XOOLSsjGBn"},{"type":"inlineCode","value":"https://github.com/ProjectPythia/Aerosol-Cloud-Interactions-cookbook","position":{"start":{"line":72,"column":1},"end":{"line":72,"column":1}},"key":"BiUetSwfEJ"},{"type":"text","value":" repository:","position":{"start":{"line":72,"column":1},"end":{"line":72,"column":1}},"key":"tBXOx2IaZ7"}],"key":"o2xp3bf9IC"},{"type":"code","lang":"bash","value":" git clone https://github.com/ProjectPythia/Aerosol-Cloud-Interactions-cookbook.git","position":{"start":{"line":74,"column":1},"end":{"line":76,"column":1}},"key":"OgDDIrk2yb"}],"key":"kQ9BoMeD56"},{"type":"listItem","spread":true,"position":{"start":{"line":78,"column":1},"end":{"line":81,"column":1}},"children":[{"type":"paragraph","position":{"start":{"line":78,"column":1},"end":{"line":78,"column":1}},"children":[{"type":"text","value":"Move into the ","position":{"start":{"line":78,"column":1},"end":{"line":78,"column":1}},"key":"ERkTk1bNN9"},{"type":"inlineCode","value":"Aerosol-Cloud-Interactions-cookbook","position":{"start":{"line":78,"column":1},"end":{"line":78,"column":1}},"key":"nHYevvsCJx"},{"type":"text","value":" directory","position":{"start":{"line":78,"column":1},"end":{"line":78,"column":1}},"key":"w9UeBqRLRg"}],"key":"p9YHSrKgOO"},{"type":"code","lang":"bash","value":"cd Aerosol-Cloud-Interactions-cookbook","position":{"start":{"line":79,"column":1},"end":{"line":81,"column":1}},"key":"GCNWpE8xBy"}],"key":"lXxjvqu0gz"},{"type":"listItem","spread":true,"position":{"start":{"line":82,"column":1},"end":{"line":86,"column":1}},"children":[{"type":"paragraph","position":{"start":{"line":82,"column":1},"end":{"line":82,"column":1}},"children":[{"type":"text","value":"Create and activate your conda environment from the ","position":{"start":{"line":82,"column":1},"end":{"line":82,"column":1}},"key":"lneVVsnbdN"},{"type":"inlineCode","value":"environment.yml","position":{"start":{"line":82,"column":1},"end":{"line":82,"column":1}},"key":"rBy21Lutxw"},{"type":"text","value":" file","position":{"start":{"line":82,"column":1},"end":{"line":82,"column":1}},"key":"nArT3lQsSz"}],"key":"BdPoxoQFcT"},{"type":"code","lang":"bash","value":"conda env create -f environment.yml\nconda activate aerosol-cookbook","position":{"start":{"line":83,"column":1},"end":{"line":86,"column":1}},"key":"GSuJeIQaT0"}],"key":"hpobKUUmS1"},{"type":"listItem","spread":true,"position":{"start":{"line":87,"column":1},"end":{"line":91,"column":1}},"children":[{"type":"paragraph","position":{"start":{"line":87,"column":1},"end":{"line":87,"column":1}},"children":[{"type":"text","value":"Move into the ","position":{"start":{"line":87,"column":1},"end":{"line":87,"column":1}},"key":"GHKmDGGCQA"},{"type":"inlineCode","value":"notebooks","position":{"start":{"line":87,"column":1},"end":{"line":87,"column":1}},"key":"J6gJy6AeJd"},{"type":"text","value":" directory and start up Jupyterlab","position":{"start":{"line":87,"column":1},"end":{"line":87,"column":1}},"key":"RCSQx4TxQT"}],"key":"U070WXakML"},{"type":"code","lang":"bash","value":"cd notebooks/\njupyter lab","position":{"start":{"line":88,"column":1},"end":{"line":91,"column":1}},"key":"kDs0FOwiAA"}],"key":"TdJ1lPeSMM"}],"key":"fh6pSFnVAU"}],"key":"Kj7xryslJC"}],"key":"jjIAjcDIDf"},"references":{"cite":{"order":[],"data":{}}},"footer":{"navigation":{"next":{"title":"How to Cite This Cookbook","url":"/notebooks/how-to-cite","group":"Preamble"}}},"domain":"http://localhost:3000"}